Workbook

Sheet Cover
B1: HINDUSTAN UNILEVER
B2: NSE:HINDUNILVR
B4: 3-STATEMENT FINANCIAL MODEL & DCF VALUATION
B6: DATE PREPARED: | F6: 46138 | I6: LAST UPDATED: | M6: =NOW() -> 46139.657
B7: PREPARED BY: AKASHDEEP MUKHERJEE
B9: TABLE OF CONTENTS | F9: VALUATION SUMMARY | K9: MODEL COLOR CODING LEGEND
B10: 1. 3 STATEMENT MODEL | F10: CURRENT MARKET PRICE | H10: 2364 | K10: BLUE TEXT: HARDCODED INPUTS & HISTORICAL ACTUALS
B12: 2. DCF VALUATION & SENSITIVITY ANALYSIS | F12: IMPLIED SHARE PRICE (DCF) | H12: =DCF!C36 -> 938.31514 | K12: BLACK TEXT: CALCULATIONS WITHIN THE SAME SHEET
F14: IMPLIED UPSIDE/ (DOWNSIDE) (AS PER IMPLIED SHARE PRICE (DCF)) | H14: =DCF!C38 -> -0.60003617 | K14: GREEN TEXT: LINKS TO OTHER SHEETS IN THIS WORKBOOK

Sheet 3 Statement Model
C1: HISTORICALS | H1: FORECASTS
B2: PARTICULARS | C2: 2021 | D2: 2022 | E2: 2023 | F2: 2024 | G2: 2025 | H2: 2026 | I2: 2027 | J2: 2028 | K2: 2029 | L2: 2030
B3: ASSUMPTIONS
B4: Segment Revenue
B5: Homecare | C5: 13957 | D5: 16570 | E5: 21223 | F5: 21882 | G5: 22958 | H5: =G5*(1+H6) -> 24105.9 | I5: =H5*(1+I6) -> 25431.725 | J5: =I5*(1+J6) -> 26957.628 | K5: =J5*(1+K6) -> 28575.086 | L5: =K5*(1+L6) -> 30289.591
D6: =(D5-C5)/C5 -> 0.18721788 | E6: =(E5-D5)/D5 -> 0.28080869 | F6: =(F5-E5)/E5 -> 0.031051218 | G6: =(G5-F5)/F5 -> 0.049172836 | H6: 0.05 | I6: 0.055 | J6: 0.06 | K6: 0.06 | L6: 0.06
B7: Beauty & Personal Care | C7: 18038 | D7: 19567 | E7: 22022 | F7: 22448 | G7: 22689 | H7: =G7*(1+H8) -> 23823.45 | I7: =H7*(1+I8) -> 25014.623 | J7: =I7*(1+J8) -> 26265.354 | K7: =J7*(1+K8) -> 27578.621 | L7: =K7*(1+L8) -> 28957.552
D8: =(D7-C7)/C7 -> 0.084765495 | E8: =(E7-D7)/D7 -> 0.12546635 | F8: =(F7-E7)/E7 -> 0.019344292 | G8: =(G7-F7)/F7 -> 0.010735923 | H8: 0.05 | I8: 0.05 | J8: 0.05 | K8: 0.05 | L8: 0.05
B9: Foods & Refreshments | C9: 13204 | D9: 14105 | E9: 14876 | F9: 15291 | G9: 15294 | H9: =G9*(1+H10) -> 15752.82 | I9: =H9*(1+I10) -> 16304.169 | J9: =I9*(1+J10) -> 16956.335 | K9: =J9*(1+K10) -> 17634.589 | L9: =K9*(1+L10) -> 18339.972
D10: =(D9-C9)/C9 -> 0.068236898 | E10: =(E9-D9)/D9 -> 0.054661468 | F10: =(F9-E9)/E9 -> 0.027897284 | G10: =(G9-F9)/F9 -> 0.00019619384 | H10: 0.03 | I10: 0.035 | J10: 0.04 | K10: 0.04 | L10: 0.04
B11: Others | C11: 1829 | D11: 2204 | E11: 2459 | F11: 2275 | G11: 2180 | H11: =G11*(1+H12) -> 2180 | I11: =H11*(1+I12) -> 2180 | J11: =I11*(1+J12) -> 2180 | K11: =J11*(1+K12) -> 2180 | L11: =K11*(1+L12) -> 2180
D12: =(D11-C11)/C11 -> 0.20503007 | E12: =(E11-D11)/D11 -> 0.11569873 | F12: =(F11-E11)/E11 -> -0.074827166 | G12: =(G11-F11)/F11 -> -0.041758242 | H12: 0 | I12: 0 | J12: 0 | K12: 0 | L12: 0
B13: Total | C13: =SUM(C11+C9+C7+C5) -> 47028 | D13: =SUM(D11+D9+D7+D5) -> 52446 | E13: =SUM(E11+E9+E7+E5) -> 60580 | F13: =SUM(F11+F9+F7+F5) -> 61896 | G13: =SUM(G11+G9+G7+G5) -> 63121 | H13: =SUM(H11+H9+H7+H5) -> 65862.17 | I13: =SUM(I11+I9+I7+I5) -> 68930.516 | J13: =SUM(J11+J9+J7+J5) -> 72359.317 | ... L13: =SUM(L11+L9+L7+L5) -> 79767.116
D14: =(D13-C13)/C13 -> 0.11520796 | E14: =(E13-D13)/D13 -> 0.15509286 | F14: =(F13-E13)/E13 -> 0.021723341 | G14: =(G13-F13)/F13 -> 0.019791263 | H14: =(H13-G13)/G13 -> 0.043427227 | I14: =(I13-H13)/H13 -> 0.046587376 | J14: =(J13-I13)/I13 -> 0.049742865 | K14: =(K13-J13)/J13 -> 0.049875799 | L14: =(L13-K13)/K13 -> 0.050005331
B16: Segment Mix
B17: Homecare | C17: =C5/C13 -> 0.29678064 | D17: =D5/D13 -> 0.31594402 | E17: =E5/E13 -> 0.35033014 | F17: =F5/F13 -> 0.3535285 | G17: =G5/G13 -> 0.36371414
B18: Beauty & Personal Care | C18: =C7/C13 -> 0.38355873 | D18: =D7/D13 -> 0.37308851 | E18: =E7/E13 -> 0.36351931 | F18: =F7/F13 -> 0.36267287 | G18: =G7/G13 -> 0.35945248
B19: Foods & Refreshments | C19: =C9/C13 -> 0.2807689 | D19: =D9/D13 -> 0.26894329 | E19: =E9/E13 -> 0.24555959 | F19: =F9/F13 -> 0.24704343 | G19: =G9/G13 -> 0.24229654
B20: Others | C20: =C11/C13 -> 0.038891724 | D20: =D11/D13 -> 0.042024177 | E20: =E11/E13 -> 0.040590954 | F20: =F11/F13 -> 0.036755202 | G20: =G11/G13 -> 0.034536842
B22: Other Income Assumptions
B23: Other Income (%) | D23: =(D86-C86)/C86 -> -0.37073171 | E23: =(E86-D86)/D86 -> 0.98449612 | F23: =(F86-E86)/E86 -> 0.58398438 | G23: =(G86-F86)/F86 -> 0.2540074 | H23: 0.06 | I23: 0.06 | J23: 0.06 | K23: 0.06 | L23: 0.06
B25: COGS Assumptions
B26: COGS (% of Revenue) | C26: =C76/C75 -> 0.47095347 | D26: =D76/D75 -> 0.49069519 | E26: =E76/E75 -> 0.52353912 | F26: =F76/F75 -> 0.48080651 | G26: =G76/G75 -> 0.48443466 | H26: 0.49 | I26: 0.49 | J26: 0.49 | K26: 0.49 | L26: 0.49
B28: Margin Assumptions
B29: EBITDA Margin (%) | C29: =C83/C75 -> 0.24721443 | D29: =D83/D75 -> 0.24514739 | E29: =E83/E75 -> 0.23355893 | F29: =F83/F75 -> 0.23689738 | G29: =G83/G75 -> 0.23527828 | H29: 0.235 | I29: 0.235 | J29: 0.235 | K29: 0.235 | L29: 0.235
B31: Working Capital Assumptions
B32: Recievable Days | C32: =(C102/C75)*365 -> 13.644425 | D32: =(D102/D75)*365 -> 15.56153 | E32: =(E102/E75)*365 -> 18.551255 | F32: =(F102/F75)*365 -> 17.673275 | G32: =(G102/G75)*365 -> 22.083538 | H32: 20 | I32: 20 | J32: 20 | K32: 20 | L32: 20
B33: Inventory Days | C33: =(C101/C76)*365 -> 58.982075 | D33: =(D101/D76)*365 -> 58.093647 | E33: =(E101/E76)*365 -> 48.922153 | F33: =(F101/F76)*365 -> 49.328965 | G33: =(G101/G76)*365 -> 52.700471 | H33: 50 | I33: 50 | J33: 50 | K33: 50 | L33: 50
B34: Payable Days | C34: =(C124/C76)*365 -> 145.05734 | D34: =(D124/D76)*365 -> 128.61162 | E34: =(E124/E76)*365 -> 110.1813 | F34: =(F124/F76)*365 -> 128.60853 | G34: =(G124/G76)*365 -> 135.06361 | H34: 130 | I34: 130 | J34: 130 | K34: 130 | L34: 130
B36: Lease Liabilities Assumption
B37: Lease Liabilities Growth (%) | D37: =(D118-C118)/C118 -> 0.069133398 | E37: =(E118-D118)/D118 -> 0.51821494 | F37: =(F118-E118)/E118 -> 0.092381524 | G37: =(G118-F118)/F118 -> 0.05601318 | H37: 0.075 | I37: 0.08 | J37: 0.085 | K37: 0.09 | L37: 0.095
B39: Other Liabilities (Provisions & Tax) Assumptions
B40: Other Liabilities (Provisions & Tax) Growth (%) | D40: =(D120-C120)/C120 -> 0.013321393 | E40: =(E120-D120)/D120 -> -0.020106054 | F40: =(F120-E120)/E120 -> 0.39526494 | G40: =(G120-F120)/F120 -> -0.045652877 | H40: 0 | I40: 0 | J40: 0 | K40: 0 | L40: 0
B42: CAPEX Assumptions
B43: CAPEX (% of Revenue) | C43: =-(C148/C75) -> 0.015756571 | D43: =-(D148/D75) -> 0.023357358 | E43: =-(E148/E75) -> 0.019379333 | F43: =-(F148/F75) -> 0.023717203 | G43: =-(G148/G75) -> 0.019866605 | H43: 0.03 | I43: 0.03 | J43: 0.03 | K43: 0.03 | L43: 0.03
B45: Tax Assumptions
B46: Tax Rate (%) | H46: 0.255 | I46: 0.255 | J46: 0.255 | K46: 0.255 | L46: 0.255
B48: Depreciation Assumptions
B49: Depreciation (% of Revenue) | C49: =C84/C75 -> 0.022837459 | D49: =D84/D75 -> 0.020802349 | E49: =E84/E75 -> 0.01876857 | F49: =F84/F75 -> 0.019645858 | G49: =G84/G75 -> 0.021466707 | H49: 0.023 | I49: 0.023 | J49: 0.023 | K49: 0.023 | L49: 0.023
B51: Expense of Employees Assumption
B52: Employee Benfit Cost (% of Revenue) | C52: =C81/C13 -> 0.050140342 | D52: =D81/D13 -> 0.048526103 | E52: =E81/E13 -> 0.047111258 | F52: =F81/F13 -> 0.048613804 | G52: =G81/G13 -> 0.048747643 | H52: =AVERAGE($C$52:$G$52) -> 0.04862783 | I52: =AVERAGE($C$52:$G$52) -> 0.04862783 | J52: =AVERAGE($C$52:$G$52) -> 0.04862783 | K52: =AVERAGE($C$52:$G$52) -> 0.04862783 | L52: =AVERAGE($C$52:$G$52) -> 0.04862783
B54: Other Expense Assumption
B55: Other Expense (% of Revenue) | C55: =C82/C13 -> 0.23169176 | D55: =D82/D13 -> 0.21563132 | E55: =E82/E13 -> 0.19579069 | F55: =F82/F13 -> 0.23368231 | G55: =G82/G13 -> 0.23153942 | H55: =AVERAGE($C$55:$G$55) -> 0.2216671 | I55: =AVERAGE($C$55:$G$55) -> 0.2216671 | J55: =AVERAGE($C$55:$G$55) -> 0.2216671 | K55: =AVERAGE($C$55:$G$55) -> 0.2216671 | L55: =AVERAGE($C$55:$G$55) -> 0.2216671
B57: Finance Cost Assumptions
B58: Finance Cost Rate (%) | H58: 0.02 | I58: 0.02 | J58: 0.02 | K58: 0.02 | L58: 0.02
B60: Opening Net PPE | C60: 5557 | D60: =C96 -> 6861 | E60: =D96 -> 7482 | F60: =E96 -> 8081 | G60: =F96 -> 9056 | H60: =G96 -> 9634 | I60: =H96 -> 10095.035 | J60: =I96 -> 10577.549 | K60: =J96 -> 11084.064 | L60: =K96 -> 11615.842
B61: Add: Capex | C61: =-C148 -> 741 | D61: =-D148 -> 1225 | E61: =-E148 -> 1174 | F61: =-F148 -> 1468 | G61: =-G148 -> 1254 | H61: =-H148 -> 1975.8651 | I61: =-I148 -> 2067.9155 | J61: =-J148 -> 2170.7795 | ... L61: =-L148 -> 2393.0135
B62: Less: Depreciation | C62: =C84 -> 1074 | D62: =D84 -> 1091 | E62: =E84 -> 1137 | F62: =F84 -> 1216 | G62: =G84 -> 1355 | H62: =H84 -> 1514.8299 | I62: =I84 -> 1585.4019 | J62: =J84 -> 1664.2643 | ... L62: =L84 -> 1834.6437
B63: Closing Net PPE | C63: 6681 | D63: 7482 | E63: 8081 | F63: 9056 | G63: 9634 | H63: =H60+H61-H62 -> 10095.035 | I63: =I60+I61-I62 -> 10577.549 | J63: =J60+J61-J62 -> 11084.064 | K63: =K60+K61-K62 -> 11615.842 | L63: =L60+L61-L62 -> 12174.212
B65: Dividend and Payout
B66: Dividend per Share | C66: =SUM(C67:C69) -> 31 | D66: =SUM(D67:D69) -> 34 | E66: =SUM(E67:E69) -> 39 | F66: =SUM(F67:F69) -> 42 | G66: =SUM(G67:G69) -> 53 | H66: 40 | I66: 40 | J66: 40 | K66: 40 | L66: 40
B67: Interim | C67: 14 | D67: 15 | E67: 17 | F67: 18 | G67: 19
B68: Special | C68: 0 | D68: 0 | E68: 0 | F68: 0 | G68: 10
B69: Final | C69: 17 | D69: 19 | E69: 22 | F69: 24 | G69: 24
B70: Dividend Payout Ratio (Total Dividend/PAT) | C70: =(C71/C91) -> 0.910625 | D70: =(D71/D91) -> 0.89906605 | E70: =(E71/E91) -> 0.90340069 | F70: =(F71/F91) -> 0.95955668 | G70: =(G71/G91) -> 1.1663077 | H70: =(H71/H91) -> 0.84410156 | I70: =(I71/I91) -> 0.80523195 | J70: =(J71/J91) -> 0.76596044 | ... L70: =(L71/L91) -> 0.69285525
B71: Total Dividends | C71: =C66*C72 -> 7285 | D71: =D66*D72 -> 7990 | E71: =E66*E72 -> 9165 | F71: =F66*F72 -> 9870 | G71: =G66*G72 -> 12455 | H71: =H66*H72 -> 9400 | I71: =I66*I72 -> 9400 | J71: =J66*J72 -> 9400 | ... L71: =L66*L72 -> 9400
B72: Total Outstanding Shares | C72: 235 | D72: 235 | E72: 235 | F72: 235 | G72: 235 | H72: 235 | I72: 235 | J72: 235 | K72: 235 | L72: 235
B74: INCOME STATEMENT
B75: Revenue from Operations | C75: =C13 -> 47028 | D75: =D13 -> 52446 | E75: =E13 -> 60580 | F75: =F13 -> 61896 | G75: =G13 -> 63121 | H75: =H13 -> 65862.17 | I75: =I13 -> 68930.516 | J75: =J13 -> 72359.317 | ... L75: =L13 -> 79767.116
B76: COGS | C76: =SUM(C77:C79) -> 22148 | D76: =SUM(D77:D79) -> 25735 | E76: =SUM(E77:E79) -> 31716 | F76: =SUM(F77:F79) -> 29760 | G76: =SUM(G77:G79) -> 30578 | H76: =H13*H26 -> 32272.463 | I76: =I13*I26 -> 33775.953 | J76: =J13*J26 -> 35456.065 | K76: =K13*K26 -> 37224.465 | L76: =L13*L26 -> 39085.887
B77: Cost of Materials Consumed | C77: 15432 | D77: 16446 | E77: 20212 | F77: 19257 | G77: 19458
B78: Purchase of Stock in Trade | C78: 7121 | D78: 9311 | E78: 11579 | F78: 10514 | G78: 11273
B79: Changes in Inventories of finished goods (including stock in trade) and Work in Progress | C79: -405 | D79: -22 | E79: -75 | F79: -11 | G79: -153
B80: Gross Profit | C80: =C75-C76 -> 24880 | D80: =D75-D76 -> 26711 | E80: =E75-E76 -> 28864 | F80: =F75-F76 -> 32136 | G80: =G75-G76 -> 32543 | H80: =H75-H76 -> 33589.707 | I80: =I75-I76 -> 35154.563 | J80: =J75-J76 -> 36903.252 | ... L80: =L75-L76 -> 40681.229
B81: Employee Benefits Expenses | C81: 2358 | D81: 2545 | E81: 2854 | F81: 3009 | G81: 3077 | H81: =H13*H52 -> 3202.7344 | I81: =I13*I52 -> 3351.9414 | J81: =J13*J52 -> 3518.6766 | K81: =K13*K52 -> 3694.1734 | L81: =L13*L52 -> 3878.9017
B82: Other Expenses | C82: 10896 | D82: 11309 | E82: 11861 | F82: 14464 | G82: 14615 | H82: =H13*H55 -> 14599.476 | I82: =I13*I55 -> 15279.627 | J82: =J13*J55 -> 16039.68 | K82: =K13*K55 -> 16839.672 | L82: =L13*L55 -> 17681.745
B83: EBITDA | C83: =C80-(C81+C82) -> 11626 | D83: =D80-(D81+D82) -> 12857 | E83: =E80-(E81+E82) -> 14149 | F83: =F80-(F81+F82) -> 14663 | G83: =G80-(G81+G82) -> 14851 | H83: =H80-(H81+H82) -> 15787.496 | I83: =I80-(I81+I82) -> 16522.994 | J83: =J80-(J81+J82) -> 17344.895 | ... L83: =L80-(L81+L82) -> 19120.582
B84: Depreciation and Amortisation Expense | C84: 1074 | D84: 1091 | E84: 1137 | F84: 1216 | G84: 1355 | H84: =H13*H49 -> 1514.8299 | I84: =I13*I49 -> 1585.4019 | J84: =J13*J49 -> 1664.2643 | K84: =K13*K49 -> 1747.2708 | L84: =L13*L49 -> 1834.6437
B85: EBIT | C85: =C83-C84 -> 10552 | D85: =D83-D84 -> 11766 | E85: =E83-E84 -> 13012 | F85: =F83-F84 -> 13447 | G85: =G83-G84 -> 13496 | H85: =H83-H84 -> 14272.666 | I85: =I83-I84 -> 14937.592 | J85: =J83-J84 -> 15680.631 | ... L85: =L83-L84 -> 17285.938
B86: Other Income | C86: 410 | D86: 258 | E86: 512 | F86: 811 | G86: 1017 | H86: =G86*(1+H23) -> 1078.02 | I86: =H86*(1+I23) -> 1142.7012 | J86: =I86*(1+J23) -> 1211.2633 | K86: =J86*(1+K23) -> 1283.9391 | L86: =K86*(1+L23) -> 1360.9754
B87: Finance Costs | C87: 117 | D87: 106 | E87: 114 | F87: 334 | G87: 395 | H87: =G87*(1+H58) -> 402.9 | I87: =H87*(1+I58) -> 410.958 | J87: =I87*(1+J58) -> 419.17716 | K87: =J87*(1+K58) -> 427.5607 | L87: =K87*(1+L58) -> 436.11192
B88: EBT | C88: =C85+C86-C87 -> 10845 | D88: =D85+D86-D87 -> 11918 | E88: =E85+E86-E87 -> 13410 | F88: =F85+F86-F87 -> 13924 | G88: =G85+G86-G87 -> 14118 | H88: =H85+H86-H87 -> 14947.786 | I88: =I85+I86-I87 -> 15669.336 | J88: =J85+J86-J87 -> 16472.717 | ... L88: =L85+L86-L87 -> 18210.802
B89: Tax Expense | C89: 2606 | D89: 2987 | E89: 3201 | F89: 3644 | G89: 3744 | H89: =H88*H46 -> 3811.6855 | I89: =I88*I46 -> 3995.6806 | J89: =J88*J46 -> 4200.5429 | K89: =K88*K46 -> 4416.3688 | L89: =L88*L46 -> 4643.7545
B90: Exceptional Items | C90: -239 | D90: -44 | E90: -64 | F90: 6 | G90: 305 | H90: 0 | I90: 0 | J90: 0 | K90: 0 | L90: 0
B91: EAT | C91: =C88+C90-C89 -> 8000 | D91: =D88+D90-D89 -> 8887 | E91: =E88+E90-E89 -> 10145 | F91: =F88+F90-F89 -> 10286 | G91: =G88+G90-G89 -> 10679 | H91: =H88+H90-H89 -> 11136.101 | I91: =I88+I90-I89 -> 11673.655 | J91: =J88+J90-J89 -> 12272.174 | ... L91: =L88+L90-L89 -> 13567.047
B93: BALANCE SHEET
B94: ASSETS
B95: Non-Current Assets
B96: Net PP&E + CWIP | C96: 6861 | D96: 7482 | E96: 8081 | F96: 9056 | G96: 9634 | H96: =H63 -> 10095.035 | I96: =I63 -> 10577.549 | J96: =J63 -> 11084.064 | K96: =K63 -> 11615.842 | L96: =L63 -> 12174.212
B97: Other Intangible Assets | C97: 45327 | D97: 45304 | E97: 45729 | F97: 45713 | G97: 45710 | H97: 45710 | I97: 45710 | J97: 45710 | K97: 45710 | L97: 45710
B98: Other Non-Current Assets | C98: 2352 | D98: 2209 | E98: 2279 | F98: 2406 | G98: 2485 | H98: 2485 | I98: 2485 | J98: 2485 | K98: 2485 | L98: 2485
B99: Total Non-Current Assets | C99: =SUM(C96:C98) -> 54540 | D99: =SUM(D96:D98) -> 54995 | E99: =SUM(E96:E98) -> 56089 | F99: =SUM(F96:F98) -> 57175 | G99: =SUM(G96:G98) -> 57829 | H99: =SUM(H96:H98) -> 58290.035 | I99: =SUM(I96:I98) -> 58772.549 | J99: =SUM(J96:J98) -> 59279.064 | ... L99: =SUM(L96:L98) -> 60369.212
B100: Current Assets
B101: Inventories | C101: 3579 | D101: 4096 | E101: 4251 | F101: 4022 | G101: 4415 | H101: =(H76/365)*H33 -> 4420.8854 | I101: =(I76/365)*I33 -> 4626.8428 | J101: =(J76/365)*J33 -> 4856.9953 | K101: =(K76/365)*K33 -> 5099.2418 | L101: =(L76/365)*L33 -> 5354.231
B102: Trade Receivables | C102: 1758 | D102: 2236 | E102: 3079 | F102: 2997 | G102: 3819 | H102: =(H13/365)*H32 -> 3608.886 | I102: =(I13/365)*I32 -> 3777.0146 | J102: =(J13/365)*J32 -> 3964.8941 | K102: =(K13/365)*K32 -> 4162.6463 | L102: =(L13/365)*L32 -> 4370.8009
B103: Total Cash and Bank Balances | C103: 4471 | D103: 3846 | E103: 4678 | F103: 7559 | G103: 7554 | H103: =H159 -> 7875.8211 | I103: =I159 -> 9993.7439 | J103: =J159 -> 12729.538 | K103: =K159 -> 16108.341 | L103: =L159 -> 20167.684
B104: Other Current Assets | C104: 4409 | D104: 5344 | E104: 4990 | F104: 6746 | G104: 6263 | H104: 7746 | I104: 7746 | J104: 7746 | K104: 7746 | L104: 7746
B105: Total Current Assets | C105: =SUM(C101:C104) -> 14217 | D105: =SUM(D101:D104) -> 15522 | E105: =SUM(E101:E104) -> 16998 | F105: =SUM(F101:F104) -> 21324 | G105: =SUM(G101:G104) -> 22051 | H105: =SUM(H101:H104) -> 23651.593 | I105: =SUM(I101:I104) -> 26143.601 | J105: =SUM(J101:J104) -> 29297.428 | ... L105: =SUM(L101:L104) -> 37638.715
B106: Total Assets | C106: =C105+C99 -> 68757 | D106: =D105+D99 -> 70517 | E106: =E105+E99 -> 73087 | F106: =F105+F99 -> 78499 | G106: =G105+G99 -> 79880 | H106: =H105+H99 -> 81941.628 | I106: =I105+I99 -> 84916.15 | J106: =J105+J99 -> 88576.492 | ... L106: =L105+L99 -> 98007.927
B108: EQUITY AND LIABILITIES
B109: Equity
B110: Equity Share Capital | C110: 235 | D110: 235 | E110: 235 | F110: 235 | G110: 235 | H110: 235 | I110: 235 | J110: 235 | K110: 235 | L110: 235
B111: Other Equity | C111: 47439 | D111: 48826 | E111: 50069 | F111: 50983 | G111: 49167 | H111: =G111+H91-H71 -> 50903.101 | I111: =H111+I91-I71 -> 53176.756 | J111: =I111+J91-J71 -> 56048.93 | K111: =J111+K91-K71 -> 59551.654 | L111: =K111+L91-L71 -> 63718.702
B112: Non-Controlling Interests | C112: 20 | D112: 26 | E112: 218 | F112: 205 | G112: 207 | H112: =AVERAGE($E$112:$G$112) -> 210 | I112: =AVERAGE($E$112:$G$112) -> 210 | J112: =AVERAGE($E$112:$G$112) -> 210 | K112: =AVERAGE($E$112:$G$112) -> 210 | L112: =AVERAGE($E$112:$G$112) -> 210
B113: Total Equity | C113: =SUM(C110:C112) -> 47694 | D113: =SUM(D110:D112) -> 49087 | E113: =SUM(E110:E112) -> 50522 | F113: =SUM(F110:F112) -> 51423 | G113: =SUM(G110:G112) -> 49609 | H113: =SUM(H110:H112) -> 51348.101 | I113: =SUM(I110:I112) -> 53621.756 | J113: =SUM(J110:J112) -> 56493.93 | ... L113: =SUM(L110:L112) -> 64163.702
B115: LIABILITIES
B116: Non-Current Liabilities
B117: Borrowings | C117: 0 | D117: 0 | E117: 0 | F117: 0 | G117: 0 | H117: 0 | I117: 0 | J117: 0 | K117: 0 | L117: 0
B118: Lease Liabilities | C118: 1027 | D118: 1098 | E118: 1667 | F118: 1821 | G118: 1923 | H118: =G118*(1+H37) -> 2067.225 | I118: =H118*(1+I37) -> 2232.603 | J118: =I118*(1+J37) -> 2422.3743 | K118: =J118*(1+K37) -> 2640.3879 | L118: =K118*(1+L37) -> 2891.2248
B119: Other Non-Current Liabilities | C119: 0 | D119: 0 | E119: 0 | F119: 0 | G119: 0 | H119: 0 | I119: =H119*(1+I37) -> 0 | J119: =I119*(1+J37) -> 0 | K119: =J119*(1+K37) -> 0 | L119: =K119*(1+L37) -> 0
...

Sheet DCF
C1: HISTORICALS | H1: FORECASTS
B2: PARTICULARS | C2: 2021 | D2: 2022 | E2: 2023 | F2: 2024 | G2: 2025 | H2: 2026 | I2: 2027 | J2: 2028 | K2: 2029 | L2: 2030
B3: EBIT | H3: ='3 Statement Model'!H85 -> 14272.666 | I3: ='3 Statement Model'!I85 -> 14937.592 | J3: ='3 Statement Model'!J85 -> 15680.631 | K3: ='3 Statement Model'!K85 -> 16462.715 | L3: ='3 Statement Model'!L85 -> 17285.938
B4: Less: Taxes on EBIT | H4: =H3*'3 Statement Model'!H46 -> 3639.5299 | I4: =I3*'3 Statement Model'!I46 -> 3809.086 | J4: =J3*'3 Statement Model'!J46 -> 3998.5609 | K4: =K3*'3 Statement Model'!K46 -> 4197.9923 | L4: =L3*'3 Statement Model'!L46 -> 4407.9143
B5: NOPAT (Net Operating Profit After Tax) | H5: =H3-H4 -> 10633.136 | I5: =I3-I4 -> 11128.506 | J5: =J3-J4 -> 11682.07 | K5: =K3-K4 -> 12264.723 | L5: =L3-L4 -> 12878.024
B6: (+) Depreciation & Amortization | H6: ='3 Statement Model'!H84 -> 1514.8299 | I6: ='3 Statement Model'!I84 -> 1585.4019 | J6: ='3 Statement Model'!J84 -> 1664.2643 | K6: ='3 Statement Model'!K84 -> 1747.2708 | L6: ='3 Statement Model'!L84 -> 1834.6437
B7: (-) Capital Expenditures (CAPEX) | H7: =-'3 Statement Model'!H148 -> 1975.8651 | I7: =-'3 Statement Model'!I148 -> 2067.9155 | J7: =-'3 Statement Model'!J148 -> 2170.7795 | K7: =-'3 Statement Model'!K148 -> 2279.0489 | L7: =-'3 Statement Model'!L148 -> 2393.0135
B8: (+/-) Changes in Working Capital | H8: =SUM('3 Statement Model'!H138:H141) -> -1099.4694 | I8: =SUM('3 Statement Model'!I138:I141) -> 161.40339 | J8: =SUM('3 Statement Model'!J138:J141) -> 180.36434 | K8: =SUM('3 Statement Model'!K138:K141) -> 189.84217 | L8: =SUM('3 Statement Model'!L138:L141) -> 199.82833
B9: Unlevered Free Cash Flow (UFCF) | H9: =H5+H6-H7+H8 -> 9072.6317 | I9: =I5+I6-I7+I8 -> 10807.396 | J9: =J5+J6-J7+J8 -> 11355.919 | K9: =K5+K6-K7+K8 -> 11922.787 | L9: =L5+L6-L7+L8 -> 12519.483
B10: Discount Period | H10: 0.5 | I10: 1.5 | J10: 2.5 | K10: 3.5 | L10: 4.5
B11: Discount Factor | H11: =1/(1+$C$24)^H10 -> 0.95346259 | I11: =1/(1+$C$24)^I10 -> 0.86678417 | J11: =1/(1+$C$24)^J10 -> 0.78798561 | K11: =1/(1+$C$24)^K10 -> 0.71635056 | L11: =1/(1+$C$24)^L10 -> 0.65122778
B12: Present Value (PV) of UFCF | H12: =H9*H11 -> 8650.415 | I12: =I9*I11 -> 9367.6798 | J12: =J9*J11 -> 8948.3009 | K12: =K9*K11 -> 8540.8949 | L12: =L9*L11 -> 8153.0349
B14: Risk Free Rate | C14: 0.07
B15: Equity Risk Premium | C15: 0.06
B16: Beta | C16: 0.5
B17: Market Capitalization | C17: 490000
B18: Cost of Equity (Ke) | C18: =C14+(C16*C15) -> 0.1
B19: Pre-Tax Cost of Debt | C19: 0.075
B20: Tax Rate | C20: 0.255
B21: After-Tax Cost of Debt (Kd) | C21: =C19*(1-C20) -> 0.055875
B22: Weight of Equity | C22: 1
B23: Weight of Debt | C23: 0
B24: WACC | C24: =(C22*C18)+(C23*C21) -> 0.1
B26: Sum of PV of UCFC | C26: =SUM(H12:L12) -> 43660.325
B27: Terminal Growth Rate | C27: 0.05
B28: Terminal Value (TV) | C28: =L9*(1+C27)/(C24-C27) -> 262909.14
B29: Implied Exit EV/EBITDA | C29: =C28/'3 Statement Model'!L83 -> 13.750059
B30: PV of Terminal Value (TV) | C30: =C28/(1+C24)^L10 -> 171213.73
B31: Enterprise Value (EV) | C31: =C30+C26 -> 214874.06
B32: Less: Total Debt | C32: ='3 Statement Model'!G117+'3 Statement Model'!G118+'3 Statement Model'!G123 -> 1924
B33: Add: Cash and Cash Equivalents | C33: ='3 Statement Model'!G103 -> 7554
B34: Implied Equity Value | C34: =C31-C32+C33 -> 220504.06
B35: Outstanding Shares (in millions) | C35: 235
B36: Implied Share Price | C36: =(C34/C35) -> 938.31514
B37: Current Market Price | C37: 2346
B38: Upside / (Downside) vs CMP | C38: =(C36-C37)/C37 -> -0.60003617
B41: SENSETIVITY ANALYSIS
C42: =C36 -> 938.31514 | D42: 0.04 | E42: 0.045 | F42: 0.05 | G42: 0.055 | H42: 0.06 | I42: 0.065 | J42: 0.07
C43: 0.085 | D43: 1069.0738 | E43: 1180.3012 | F43: 1323.3079 | G43: 1513.9836 | H43: 1780.9294 | I43: 2181.3482 | J43: 2848.7128
C44: 0.09 | D44: 965.88405 | E44: 1053.4456 | F44: 1162.8975 | G44: 1303.6213 | H44: 1491.2531 | I44: 1753.9377 | J44: 2147.9645
C45: 0.095 | D45: 881.458 | E45: 951.96081 | F45: 1038.1309 | G45: 1145.8435 | H45: 1284.3312 | I45: 1468.9814 | J45: 1727.4917
C46: 0.1 | D46: 811.10467 | E46: 868.92761 | F46: 938.31514 | G46: 1023.1221 | H46: 1129.1308 | I46: 1265.4278 | J46: 1447.157
C47: 0.105 | D47: 751.57642 | E47: 799.73303 | F47: 856.6454 | G47: 924.94023 | H47: 1008.4117 | I47: 1112.751 | J47: 1246.9016
C48: 0.11 | D48: 700.55354 | E48: 741.18352 | F48: 788.58518 | G48: 844.60531 | H48: 911.82948 | I48: 993.99234 | J48: 1096.6959
C49: 0.115 | D49: 656.33489 | E49: 690.99797 | F49: 730.99383 | G49: 777.65568 | H49: 832.80149 | I49: 898.97647 | J49: 979.85699
